YehuoFreertosNeiheShixianYuYingyongKaifaShizhanFix1/README.md
YehuoFreertosNeiheShixianYuYingyongKaifaShizhanFix1/__init__.py
YehuoFreertosNeiheShixianYuYingyongKaifaShizhanFix1/__main__.py
YehuoFreertosNeiheShixianYuYingyongKaifaShizhanFix1/file.epub
YehuoFreertosNeiheShixianYuYingyongKaifaShizhanFix1/index.html
YehuoFreertosNeiheShixianYuYingyongKaifaShizhanFix1/css/__init__.py
YehuoFreertosNeiheShixianYuYingyongKaifaShizhanFix1/css/annotations.css
YehuoFreertosNeiheShixianYuYingyongKaifaShizhanFix1/css/main.css
YehuoFreertosNeiheShixianYuYingyongKaifaShizhanFix1/css/normalize.css
YehuoFreertosNeiheShixianYuYingyongKaifaShizhanFix1/css/popup.css
YehuoFreertosNeiheShixianYuYingyongKaifaShizhanFix1/font/__init__.py
YehuoFreertosNeiheShixianYuYingyongKaifaShizhanFix1/font/fontello.eot
YehuoFreertosNeiheShixianYuYingyongKaifaShizhanFix1/font/fontello.svg
YehuoFreertosNeiheShixianYuYingyongKaifaShizhanFix1/font/fontello.ttf
YehuoFreertosNeiheShixianYuYingyongKaifaShizhanFix1/font/fontello.woff
YehuoFreertosNeiheShixianYuYingyongKaifaShizhanFix1/img/__init__.py
YehuoFreertosNeiheShixianYuYingyongKaifaShizhanFix1/img/annotator-glyph-sprite.png
YehuoFreertosNeiheShixianYuYingyongKaifaShizhanFix1/img/annotator-icon-sprite.png
YehuoFreertosNeiheShixianYuYingyongKaifaShizhanFix1/img/apple-touch-icon.png
YehuoFreertosNeiheShixianYuYingyongKaifaShizhanFix1/img/cancelfullscreen.png
YehuoFreertosNeiheShixianYuYingyongKaifaShizhanFix1/img/close.png
YehuoFreertosNeiheShixianYuYingyongKaifaShizhanFix1/img/fullscreen.png
YehuoFreertosNeiheShixianYuYingyongKaifaShizhanFix1/img/loader.gif
YehuoFreertosNeiheShixianYuYingyongKaifaShizhanFix1/img/menu-icon.png
YehuoFreertosNeiheShixianYuYingyongKaifaShizhanFix1/img/save.png
YehuoFreertosNeiheShixianYuYingyongKaifaShizhanFix1/img/saved.png
YehuoFreertosNeiheShixianYuYingyongKaifaShizhanFix1/img/settings-s.png
YehuoFreertosNeiheShixianYuYingyongKaifaShizhanFix1/img/settings.png
yehuo_freertos_neihe_shixian_yu_yingyong_kaifa_shizhan_fix1-2025.3.24.0.dist-info/METADATA
yehuo_freertos_neihe_shixian_yu_yingyong_kaifa_shizhan_fix1-2025.3.24.0.dist-info/WHEEL
yehuo_freertos_neihe_shixian_yu_yingyong_kaifa_shizhan_fix1-2025.3.24.0.dist-info/entry_points.txt
yehuo_freertos_neihe_shixian_yu_yingyong_kaifa_shizhan_fix1-2025.3.24.0.dist-info/top_level.txt
yehuo_freertos_neihe_shixian_yu_yingyong_kaifa_shizhan_fix1-2025.3.24.0.dist-info/RECORD
